wisemodel_hub/__init__.py
wisemodel_hub/auth.py
wisemodel_hub/constants.py
wisemodel_hub/download_script.py
wisemodel_hub/download_with_resume.py
wisemodel_hub/downloader.py
wisemodel_hub/git_downloader.py
wisemodel_hub/git_uploader.py
wisemodel_hub/parallel_download_with_resume.py
wisemodel_hub/upload_script.py
wisemodel_hub/uploader.py
wisemodel_hub/utils.py
wisemodel_hub-0.5.0.dist-info/licenses/LICENSE
wisemodel_hub-0.5.0.dist-info/METADATA
wisemodel_hub-0.5.0.dist-info/WHEEL
wisemodel_hub-0.5.0.dist-info/entry_points.txt
wisemodel_hub-0.5.0.dist-info/top_level.txt
wisemodel_hub-0.5.0.dist-info/RECORD
