Metadata-Version: 2.4
Name: wisemodel_hub
Version: 0.5.0
Summary: Client library to download and publish models, datasets and other repos on the wisemodel.cn hub
Home-page: https://github.com/wisemodel/wisemodel-hub
Author: 始智AI
Author-email: 4498237@qq.com
License: Apache
Keywords: model-hub machine-learning models natural-language-processing deep-learning pytorch pretrained-models
Classifier: Intended Audience :: Developers
Classifier: Intended Audience :: Education
Classifier: Intended Audience :: Science/Research
Classifier: License :: OSI Approved :: Apache Software License
Classifier: Operating System :: OS Independent
Classifier: Programming Language :: Python :: 3
Classifier: Programming Language :: Python :: 3 :: Only
Classifier: Programming Language :: Python :: 3.8
Classifier: Programming Language :: Python :: 3.9
Classifier: Programming Language :: Python :: 3.10
Classifier: Programming Language :: Python :: 3.11
Classifier: Programming Language :: Python :: 3.12
Classifier: Topic :: Scientific/Engineering :: Artificial Intelligence
Requires-Python: >=3.8.0
License-File: LICENSE
Requires-Dist: packaging>=20.9
Requires-Dist: requests>=2.20.0
Requires-Dist: tqdm>=4.64.1
Requires-Dist: python-gitlab>=5.0.0
Requires-Dist: ipywidgets>=8.1.5
Provides-Extra: torch
Requires-Dist: torch; extra == "torch"
Requires-Dist: safetensors[torch]; extra == "torch"
Provides-Extra: typing
Requires-Dist: typing-extensions>=4.8.0; extra == "typing"
Requires-Dist: types-PyYAML; extra == "typing"
Requires-Dist: types-requests; extra == "typing"
Requires-Dist: types-simplejson; extra == "typing"
Requires-Dist: types-toml; extra == "typing"
Requires-Dist: types-tqdm; extra == "typing"
Requires-Dist: types-urllib3; extra == "typing"
Provides-Extra: quality
Requires-Dist: ruff>=0.5.0; extra == "quality"
Requires-Dist: mypy==1.5.1; extra == "quality"
Requires-Dist: libcst==1.4.0; extra == "quality"
Provides-Extra: doc
Requires-Dist: sphinx>=8.1.0; extra == "doc"
Requires-Dist: sphinx-autobuild>=2024.10.3; extra == "doc"
Requires-Dist: sphinx_rtd_theme>=3.0.0; extra == "doc"
Requires-Dist: myst_parser>=4.0.0; extra == "doc"
Requires-Dist: sphinx-markdown-tables>=0.0.17; extra == "doc"
Provides-Extra: all
Requires-Dist: ruff>=0.5.0; extra == "all"
Requires-Dist: mypy==1.5.1; extra == "all"
Requires-Dist: libcst==1.4.0; extra == "all"
Requires-Dist: typing-extensions>=4.8.0; extra == "all"
Requires-Dist: types-PyYAML; extra == "all"
Requires-Dist: types-requests; extra == "all"
Requires-Dist: types-simplejson; extra == "all"
Requires-Dist: types-toml; extra == "all"
Requires-Dist: types-tqdm; extra == "all"
Requires-Dist: types-urllib3; extra == "all"
Requires-Dist: sphinx>=8.1.0; extra == "all"
Requires-Dist: sphinx-autobuild>=2024.10.3; extra == "all"
Requires-Dist: sphinx_rtd_theme>=3.0.0; extra == "all"
Requires-Dist: myst_parser>=4.0.0; extra == "all"
Requires-Dist: sphinx-markdown-tables>=0.0.17; extra == "all"
Provides-Extra: dev
Requires-Dist: ruff>=0.5.0; extra == "dev"
Requires-Dist: mypy==1.5.1; extra == "dev"
Requires-Dist: libcst==1.4.0; extra == "dev"
Requires-Dist: typing-extensions>=4.8.0; extra == "dev"
Requires-Dist: types-PyYAML; extra == "dev"
Requires-Dist: types-requests; extra == "dev"
Requires-Dist: types-simplejson; extra == "dev"
Requires-Dist: types-toml; extra == "dev"
Requires-Dist: types-tqdm; extra == "dev"
Requires-Dist: types-urllib3; extra == "dev"
Requires-Dist: sphinx>=8.1.0; extra == "dev"
Requires-Dist: sphinx-autobuild>=2024.10.3; extra == "dev"
Requires-Dist: sphinx_rtd_theme>=3.0.0; extra == "dev"
Requires-Dist: myst_parser>=4.0.0; extra == "dev"
Requires-Dist: sphinx-markdown-tables>=0.0.17; extra == "dev"
Dynamic: author
Dynamic: author-email
Dynamic: classifier
Dynamic: description
Dynamic: description-content-type
Dynamic: home-page
Dynamic: keywords
Dynamic: license
Dynamic: license-file
Dynamic: provides-extra
Dynamic: requires-dist
Dynamic: requires-python
Dynamic: summary
